surframe_ucodec_pro/__init__.py
surframe_ucodec_pro-0.16.0.post3.dist-info/METADATA
surframe_ucodec_pro-0.16.0.post3.dist-info/WHEEL
surframe_ucodec_pro-0.16.0.post3.dist-info/top_level.txt
surframe_ucodec_pro-0.16.0.post3.dist-info/RECORD
