Metadata-Version: 2.4
Name: surframe-ucodec-pro
Version: 0.16.0.post3
Summary: Marker package for SURFRAME U-Codec PRO (no plugin code).
Author: Christ10-8
License-Expression: LicenseRef-Proprietary
Classifier: Programming Language :: Python :: 3
Classifier: Programming Language :: Python :: 3 :: Only
Classifier: Operating System :: OS Independent
Requires-Python: >=3.10
